{
  "discId": "44U21.Qztklxiv7MZs1jadDnNFo-",
  "artist": "Screeching Weasel",
  "year": "1996",
  "album": "Bark Like a Dog",
  "albumArt": "https://coverartarchive.org/release/e782f11a-a33b-3cb8-b9a1-1e0ac2e166ac/front",
  "tracks": [
    "Get Off My Back",
    "Cool Kids",
    "The First Day of Summer",
    "You'll Be in My Dreams Today",
    "You Blister My Paint",
    "Stupid Girl",
    "Phasers on Kill",
    "Handcuffed to You",
    "(She Got) Electroshocked",
    "It's Not Enough",
    "I Will Always Be There",
    "Your Name Is Tattooed on My Heart"
  ]
}