{
  "discId": "7sR.zGlUpM6wwWDfnKpqUsLle6Y-",
  "artist": "Ween",
  "year": "1994",
  "album": "Chocolate and Cheese",
  "albumArt": "https://coverartarchive.org/release/febc2eb1-e76f-4155-ab21-2422f014bc33/front",
  "tracks": [
    "Take Me Away",
    "Spinal Meningitis (Got Me Down)",
    "Freedom of '76",
    "I Can't Put My Finger on It",
    "A Tear for Eddie",
    "Roses Are Free",
    "Baby Bitch",
    "Mister, Would You Please Help My Pony?",
    "Drifter in the Dark",
    "Voodoo Lady",
    "Joppa Road",
    "Candi",
    "Buenas tardes amigo",
    "The HIV Song",
    "What Deaner Was Talkin' About",
    "Don't Shit Where You Eat"
  ]
}
