{
  "discId": "mq8b4A.7BQdrKDpLjWW65OrNdck-",
  "artist": "Various Artists",
  "year": "1997",
  "album": "Capitol Cheese Spring 1997 [Promo Sampler]",
  "albumArt": "https://i.discogs.com/XQJAYZkSO4lZD0mOkgH9penb8csZfPEYe0I1gKKurbM/rs:fit/g:sm/q:90/h:550/w:600/czM6Ly9kaXNjb2dz/LWRhdGFiYXNlLWlt/YWdlcy9SLTQyMDUz/NDQtMTY4MTMxMDQ0/My03NjYwLnBuZw.jpeg",
  "tracks": [
    "Supergrass - Going Out",
    "Luscious Jackson- Under Your Skin (The Sheds Lbs Mix)",
    "Bettie Serveert - Co-Coward",
    "Spearhead - Rebel Music (3 O'Clock Road Block)",
    "The Dandy Warhols - I Love You",
    "Less Than Jake - Automatic",
    "Smoking Popes - Pure Imagination",
    "Meredith Brooks - Wash My Hands",
    "Stir - Stale",
    "Vic Chesnutt - Ladle",
    "Nil LAra - Baby",
    "Skeleton Key - Wide Open",
    "US3 - Come On Everybody (Get Down) (Q - Burns Abstract Message Remix_",
    "Blind Melon - Soul One",
    "Jimmy Eat World - Rockstar",
    "Dink - Drive",
    "A Don Piper Situation - Try To Laugh",
    "Mazzy Star - I've Been Let Down"
  ]
}
