{
  "discId": "qkB9Dt9.VsIYivGHoKOPYvfzbps-",
  "artist": "Man or Astro‐Man?",
  "year": "1995",
  "album": "Intravenous Television Continuum",
  "albumArt": "https://coverartarchive.org/release/d2be3c08-e242-4839-bb26-358b3a36a342/front",
  "tracks": [
    "Immersion Static",
    "Put Your Finger in the Socket (Maximum Voltage version)",
    "Nitrous Burn Out 2012",
    "Tetsuwan Atomu",
    "Max Q (Nielson Rating video version)",
    "Max Q (Reverse Sync Moog version)",
    "Jetson's Theme",
    "Invasion of the Dragonmen (Alternate Universe Mosrite version)",
    "Bionic Futures",
    "Tomorrow Plus X (Time Travel Through Sleep Deprivation mix)",
    "Out of Limits",
    "Calling Hong Kong",
    "Munster's Theme",
    "Principles Unknown",
    "Everyone's Favorite Martian",
    "Deuces Wild",
    "Cool Your Jets"
  ]
}
