{
  "discId": "tz0QC3wGJ4L4zzqDfiRnJyykF7I-",
  "artist": "The Tossers",
  "year": "1996",
  "album": "We'll Never Be Sober Again",
  "albumArt": "https://i.discogs.com/Oni6YHy34k6Ei1riRoyDIzySMx5I-r83YgOx9b-FfTk/rs:fit/g:sm/q:90/h:294/w:300/czM6Ly9kaXNjb2dz/LWRhdGFiYXNlLWlt/YWdlcy9SLTIyNDAz/MjktMTI3MTczNjk1/Ny5qcGVn.jpeg",
  "tracks": [
    "Waitin' For The Wagon",
    "When You Get Here",
    "Dancin' Shoes",
    "Buckets Of Beer",
    "Aye Sir",
    "Thermometer",
    "I Know Where I'm Goin'",
    "Chelsea Girls",
    "Sleepin' In A Dustbin",
    "30 Days",
    "Irish Whiskey",
    "Fall On The Floor",
    "Everything's Bad",
    "Alone"
  ]
}
